setup.py
deep_security_api.egg-info/PKG-INFO
deep_security_api.egg-info/SOURCES.txt
deep_security_api.egg-info/dependency_links.txt
deep_security_api.egg-info/requires.txt
deep_security_api.egg-info/top_level.txt
deepsecurity/__init__.py
deepsecurity/api_client.py
deepsecurity/configuration.py
deepsecurity/rest.py
deepsecurity/api/__init__.py
deepsecurity/api/administrator_roles_api.py
deepsecurity/api/administrators_api.py
deepsecurity/api/agent_deployment_scripts_api.py
deepsecurity/api/agent_version_control_profiles_api.py
deepsecurity/api/agent_version_controls_api.py
deepsecurity/api/anti_malware_configurations_api.py
deepsecurity/api/api_keys_api.py
deepsecurity/api/api_usage_api.py
deepsecurity/api/application_types_api.py
deepsecurity/api/aws_connector_settings_api.py
deepsecurity/api/aws_connectors_api.py
deepsecurity/api/azure_connectors_api.py
deepsecurity/api/certificates_api.py
deepsecurity/api/computer_firewall_rule_assignments_api.py
deepsecurity/api/computer_firewall_rule_details_api.py
deepsecurity/api/computer_groups_api.py
deepsecurity/api/computer_integrity_monitoring_rule_assignments__recommendations_api.py
deepsecurity/api/computer_integrity_monitoring_rule_details_api.py
deepsecurity/api/computer_intrusion_prevention_application_type_details_api.py
deepsecurity/api/computer_intrusion_prevention_rule_assignments__recommendations_api.py
deepsecurity/api/computer_intrusion_prevention_rule_details_api.py
deepsecurity/api/computer_log_inspection_rule_assignments__recommendations_api.py
deepsecurity/api/computer_log_inspection_rule_details_api.py
deepsecurity/api/computer_move_tasks_api.py
deepsecurity/api/computers_api.py
deepsecurity/api/contacts_api.py
deepsecurity/api/contexts_api.py
deepsecurity/api/directory_lists_api.py
deepsecurity/api/endpoint_basecamp_agent_deployment_scripts_api.py
deepsecurity/api/event_based_tasks_api.py
deepsecurity/api/file_extension_lists_api.py
deepsecurity/api/file_lists_api.py
deepsecurity/api/firewall_rules_api.py
deepsecurity/api/gcp_connector_actions_api.py
deepsecurity/api/gcp_connectors_api.py
deepsecurity/api/global_rules_api.py
deepsecurity/api/integrity_monitoring_rules_api.py
