Metadata-Version: 1.0
Name: deep-security-api
Version: 20.0.463
Summary: Trend Micro Deep Security API
Home-page: UNKNOWN
Author: UNKNOWN
Author-email: UNKNOWN
License: UNKNOWN
Keywords: Swagger,Trend Micro Deep Security API
Platform: UNKNOWN
